{"solutions": [{"routes": [{"vehicle": {"group": "1.5XT", "code": "R1-XT1.5T-01", "lat": 10.761124256132712, "lng": 106.63281628678588, "endLat": 10.761124256132712, "endLng": 106.63281628678588, "startWorkingTime": "2019-12-05 09:00:00.0", "endWorkingTime": "2019-12-05 16:00:00.0", "availableCapacity": 1500000, "availableCbm": 1231.2}, "elements": [{"code": "R1_HCM", "address": "Qu\u1eadn T\u00e2n Ph\u00fa", "lat": 10.761124256132712, "lng": 106.63281628678588, "arrivalTime": "2019-12-05 09:00:01", "departureTime": "2019-12-05 09:00:01", "description": "", "orderCode": 0, "load": 0, "distance": 0}, {"code": "3589237", "address": "Qu\u1eadn 5", "lat": 10.7570661, "lng": 106.6597319, "arrivalTime": "2019-12-05 09:13:29", "departureTime": "2019-12-05 09:28:29", "description": "", "orderCode": "0030880", "load": 85620, "distance": 4, "items": [{"code": "187060", "itemType": "Adult", "weight": 11520, "quantity": 24, "cbm": 0.03108, "description": ""}, {"code": "187061", "itemType": "Ensure", "weight": 74100, "quantity": 300, "cbm": 0.1434, "description": ""}]}, {"code": "3589287", "address": "Qu\u1eadn 5", "lat": 10.7558541, "lng": 106.6617815, "arrivalTime": "2019-12-05 09:29:44", "departureTime": "2019-12-05 09:44:44", "description": "", "orderCode": "0030997", "load": 90324, "distance": 4, "items": [{"code": "187110", "itemType": "Similac", "weight": 4704, "quantity": 48, "cbm": 0.010128, "description": ""}]}, {"code": "3589287", "address": "Qu\u1eadn 5", "lat": 10.7558541, "lng": 106.6617815, "arrivalTime": "2019-12-05 09:29:44", "departureTime": "2019-12-05 09:44:44", "description": "", "orderCode": "0030998", "load": 115284, "distance": 4, "items": [{"code": "187111", "itemType": "Similac", "weight": 24960, "quantity": 48, "cbm": 0.06216, "description": ""}]}, {"code": "1156189", "address": "Qu\u1eadn 5", "lat": 10.7571014, "lng": 106.6782649, "arrivalTime": "2019-12-05 09:50:54", "departureTime": "2019-12-05 10:05:54", "description": "", "orderCode": "0031059", "load": 477354, "distance": 6, "items": [{"code": "186965", "itemType": "Pediasure", "weight": 177030, "quantity": 90, "cbm": 0.4608, "description": ""}, {"code": "186966", "itemType": "Pediasure", "weight": 185040, "quantity": 120, "cbm": 0.95244, "description": ""}]}, {"code": "1213989", "address": "Qu\u1eadn 1", "lat": 10.7688293, "lng": 106.6858546, "arrivalTime": "2019-12-05 10:11:51", "departureTime": "2019-12-05 10:41:51", "description": "", "orderCode": "0030875", "load": 687594, "distance": 7, "items": [{"code": "187011", "itemType": "Ensure", "weight": 210240, "quantity": 720, "cbm": 0.35568, "description": ""}]}, {"code": "1213989", "address": "Qu\u1eadn 1", "lat": 10.7688293, "lng": 106.6858546, "arrivalTime": "2019-12-05 10:11:51", "departureTime": "2019-12-05 10:41:51", "description": "", "orderCode": "0030876", "load": 700026, "distance": 7, "items": [{"code": "187012", "itemType": "Adult", "weight": 12432, "quantity": 24, "cbm": 0.03108, "description": ""}]}, {"code": "3909437", "address": "Qu\u1eadn Th\u1ee7 \u0110\u1ee9c", "lat": 10.865694, "lng": 106.745507, "arrivalTime": "2019-12-05 11:26:32", "departureTime": "2019-12-05 11:32:44", "description": "", "orderCode": "0030986", "load": 733170, "distance": 21, "items": [{"code": "187090", "itemType": "Ensure", "weight": 12408, "quantity": 24, "cbm": 0.03108, "description": ""}, {"code": "187091", "itemType": "Ensure", "weight": 20736, "quantity": 72, "cbm": 0.036792, "description": ""}]}, {"code": "4254287", "address": "Qu\u1eadn Th\u1ee7 \u0110\u1ee9c", "lat": 10.8622729, "lng": 106.7775038, "arrivalTime": "2019-12-05 11:50:04", "departureTime": "2019-12-05 11:57:02", "description": "", "orderCode": "0030994", "load": 894060, "distance": 26, "items": [{"code": "187102", "itemType": "Ensure", "weight": 32760, "quantity": 120, "cbm": 0.05736, "description": ""}, {"code": "187103", "itemType": "Adult", "weight": 15600, "quantity": 60, "cbm": 0.02868, "description": ""}, {"code": "187104", "itemType": "Ensure", "weight": 105120, "quantity": 360, "cbm": 0.17784, "description": ""}, {"code": "187105", "itemType": "Ensure", "weight": 7410, "quantity": 30, "cbm": 0.01434, "description": ""}]}, {"code": "3873987", "address": "Qu\u1eadn Th\u1ee7 \u0110\u1ee9c", "lat": 10.8615372, "lng": 106.7799083, "arrivalTime": "2019-12-05 12:00:53", "departureTime": "2019-12-05 12:15:53", "description": "", "orderCode": "0031141", "load": 1036002, "distance": 27, "items": [{"code": "187147", "itemType": "Ensure", "weight": 16380, "quantity": 60, "cbm": 0.02868, "description": ""}, {"code": "187148", "itemType": "Adult", "weight": 24864, "quantity": 48, "cbm": 0.06216, "description": ""}, {"code": "187149", "itemType": "Ensure", "weight": 56064, "quantity": 192, "cbm": 0.094848, "description": ""}, {"code": "187150", "itemType": "Ensure", "weight": 37224, "quantity": 72, "cbm": 0.09324, "description": ""}, {"code": "187151", "itemType": "Ensure", "weight": 7410, "quantity": 30, "cbm": 0.01434, "description": ""}]}, {"code": "3912287", "address": "Qu\u1eadn 9", "lat": 10.8472532, "lng": 106.7762454, "arrivalTime": "2019-12-05 12:22:44", "departureTime": "2019-12-05 12:29:00", "description": "", "orderCode": "0031025", "load": 1078842, "distance": 29, "items": [{"code": "187130", "itemType": "Adult", "weight": 7800, "quantity": 30, "cbm": 0.01434, "description": ""}, {"code": "187131", "itemType": "Ensure", "weight": 35040, "quantity": 120, "cbm": 0.05928, "description": ""}]}, {"code": "3875887", "address": "Qu\u1eadn 2", "lat": 10.7836543, "lng": 106.7690294, "arrivalTime": "2019-12-05 12:58:48", "departureTime": "2019-12-05 13:05:36", "description": "", "orderCode": "0031030", "load": 1211802, "distance": 38, "items": [{"code": "187140", "itemType": "Adult", "weight": 23400, "quantity": 90, "cbm": 0.04302, "description": ""}, {"code": "187141", "itemType": "Adult", "weight": 37296, "quantity": 72, "cbm": 0.09324, "description": ""}, {"code": "187142", "itemType": "Ensure", "weight": 35040, "quantity": 120, "cbm": 0.05928, "description": ""}, {"code": "187143", "itemType": "Ensure", "weight": 37224, "quantity": 72, "cbm": 0.09324, "description": ""}]}, {"code": "1691339", "address": "Qu\u1eadn 4", "lat": 10.7611037, "lng": 106.6997136, "arrivalTime": "2019-12-05 13:37:32", "departureTime": "2019-12-05 13:52:32", "description": "", "orderCode": "0031086", "load": 1220262, "distance": 48, "items": [{"code": "186991", "itemType": "Adult", "weight": 8460, "quantity": 2, "cbm": 0.025028, "description": ""}]}, {"code": "4270037", "address": "Qu\u1eadn 1", "lat": 10.7634963, "lng": 106.6897523, "arrivalTime": "2019-12-05 13:59:25", "departureTime": "2019-12-05 14:05:33", "description": "", "orderCode": "0030883", "load": 1241286, "distance": 50, "items": [{"code": "187066", "itemType": "Ensure", "weight": 21024, "quantity": 72, "cbm": 0.035568, "description": ""}]}, {"code": "1107139", "address": "Qu\u1eadn 1", "lat": 10.768228, "lng": 106.68583, "arrivalTime": "2019-12-05 14:08:08", "departureTime": "2019-12-05 14:23:08", "description": "", "orderCode": "0030981", "load": 1247502, "distance": 50, "items": [{"code": "187081", "itemType": "Adult", "weight": 6216, "quantity": 12, "cbm": 0.01554, "description": ""}]}, {"code": "1107139", "address": "Qu\u1eadn 1", "lat": 10.768228, "lng": 106.68583, "arrivalTime": "2019-12-05 14:08:08", "departureTime": "2019-12-05 14:23:08", "description": "", "orderCode": "0030980", "load": 1282542, "distance": 50, "items": [{"code": "187080", "itemType": "Ensure", "weight": 35040, "quantity": 120, "cbm": 0.05928, "description": ""}]}, {"code": "1107139", "address": "Qu\u1eadn 1", "lat": 10.768228, "lng": 106.68583, "arrivalTime": "2019-12-05 14:08:08", "departureTime": "2019-12-05 14:23:08", "description": "", "orderCode": "0030884", "load": 1298142, "distance": 50, "items": [{"code": "187067", "itemType": "Adult", "weight": 15600, "quantity": 60, "cbm": 0.02868, "description": ""}]}, {"code": "3918137", "address": "Qu\u1eadn 10", "lat": 10.7686551, "lng": 106.670189, "arrivalTime": "2019-12-05 14:28:49", "departureTime": "2019-12-05 14:35:02", "description": "", "orderCode": "0031002", "load": 1332942, "distance": 51, "items": [{"code": "187123", "itemType": "Pediasure", "weight": 34800, "quantity": 120, "cbm": 0.05844, "description": ""}]}, {"code": "1156689", "address": "Qu\u1eadn 10", "lat": 10.7627583, "lng": 106.6718096, "arrivalTime": "2019-12-05 14:37:28", "departureTime": "2019-12-05 14:52:28", "description": "", "orderCode": "0031101", "load": 1367982, "distance": 51, "items": [{"code": "187018", "itemType": "Ensure", "weight": 35040, "quantity": 120, "cbm": 0.05928, "description": ""}]}, {"code": "1156689", "address": "Qu\u1eadn 10", "lat": 10.7627583, "lng": 106.6718096, "arrivalTime": "2019-12-05 14:37:28", "departureTime": "2019-12-05 14:52:28", "description": "", "orderCode": "0031102", "load": 1378062, "distance": 51, "items": [{"code": "187019", "itemType": "Grow", "weight": 10080, "quantity": 48, "cbm": 0.014736, "description": ""}]}, {"code": "1371539", "address": "Qu\u1eadn 5", "lat": 10.7574689, "lng": 106.6615947, "arrivalTime": "2019-12-05 14:58:05", "departureTime": "2019-12-05 15:13:05", "description": "", "orderCode": "0031023", "load": 1413102, "distance": 52, "items": [{"code": "187124", "itemType": "Ensure", "weight": 35040, "quantity": 120, "cbm": 0.05928, "description": ""}]}, {"code": "R1_HCM", "address": "Qu\u1eadn T\u00e2n Ph\u00fa", "lat": 10.761124256132712, "lng": 106.63281628678588, "arrivalTime": "2019-12-05 15:24:40", "departureTime": "2019-12-05 15:24:40", "description": "", "orderCode": 0, "load": 0, "distance": 52}], "distance": 52}, {"vehicle": {"group": "1.7XT", "code": "R1-XT1.7T-01", "lat": 10.761124256132712, "lng": 106.63281628678588, "endLat": 10.761124256132712, "endLng": 106.63281628678588, "startWorkingTime": "2019-12-05 09:00:00.0", "endWorkingTime": "2019-12-05 16:00:00.0", "availableCapacity": 1700000, "availableCbm": 1360.8}, "elements": [{"code": "R1_HCM", "address": "Qu\u1eadn T\u00e2n Ph\u00fa", "lat": 10.761124256132712, "lng": 106.63281628678588, "arrivalTime": "2019-12-05 09:00:00", "departureTime": "2019-12-05 09:00:00", "description": "", "orderCode": 0, "load": 0, "distance": 0}, {"code": "1164089", "address": "Qu\u1eadn 8", "lat": 10.7388909675498, "lng": 106.656071476196, "arrivalTime": "2019-12-05 09:19:04", "departureTime": "2019-12-05 09:34:04", "description": "", "orderCode": "0031136", "load": 141375, "distance": 6, "items": [{"code": "187051", "itemType": "Adult", "weight": 23400, "quantity": 90, "cbm": 0.04302, "description": ""}, {"code": "187052", "itemType": "Adult", "weight": 3108, "quantity": 6, "cbm": 0.00777, "description": ""}, {"code": "187053", "itemType": "Grow", "weight": 21480, "quantity": 12, "cbm": 0.111708, "description": ""}, {"code": "187054", "itemType": "Ensure", "weight": 35040, "quantity": 120, "cbm": 0.05928, "description": ""}, {"code": "187055", "itemType": "Ensure", "weight": 9603, "quantity": 9, "cbm": 0.026694, "description": ""}, {"code": "187056", "itemType": "Pediasure", "weight": 18504, "quantity": 12, "cbm": 0.095244, "description": ""}, {"code": "187057", "itemType": "Grow", "weight": 30240, "quantity": 144, "cbm": 0.044208, "description": ""}]}, {"code": "2506589", "address": "Qu\u1eadn 5", "lat": 10.7555408, "lng": 106.6701378, "arrivalTime": "2019-12-05 09:44:10", "departureTime": "2019-12-05 09:59:10", "description": "", "orderCode": "0031058", "load": 377415, "distance": 9, "items": [{"code": "186964", "itemType": "Pediasure", "weight": 236040, "quantity": 120, "cbm": 0.6144, "description": ""}]}, {"code": "3892137", "address": "Qu\u1eadn 3", "lat": 10.7735376, "lng": 106.6809097, "arrivalTime": "2019-12-05 10:07:45", "departureTime": "2019-12-05 10:14:15", "description": "", "orderCode": "0031024", "load": 458391, "distance": 11, "items": [{"code": "187125", "itemType": "Ensure", "weight": 3276, "quantity": 12, "cbm": 0.005736, "description": ""}, {"code": "187126", "itemType": "Adult", "weight": 1554, "quantity": 3, "cbm": 0.003885, "description": ""}, {"code": "187127", "itemType": "Ensure", "weight": 70080, "quantity": 240, "cbm": 0.11856, "description": ""}, {"code": "187128", "itemType": "Ensure", "weight": 3102, "quantity": 6, "cbm": 0.00777, "description": ""}, {"code": "187129", "itemType": "Ensure", "weight": 2964, "quantity": 12, "cbm": 0.005736, "description": ""}]}, {"code": "3102587", "address": "Qu\u1eadn 3", "lat": 10.7843522, "lng": 106.6840268, "arrivalTime": "2019-12-05 10:20:06", "departureTime": "2019-12-05 10:35:06", "description": "", "orderCode": "0030878", "load": 598551, "distance": 12, "items": [{"code": "187015", "itemType": "Ensure", "weight": 140160, "quantity": 480, "cbm": 0.23712, "description": ""}]}, {"code": "3917887", "address": "Qu\u1eadn Ph\u00fa Nhu\u1eadn", "lat": 10.8000737, "lng": 106.6841466, "arrivalTime": "2019-12-05 10:43:23", "departureTime": "2019-12-05 10:49:37", "description": "", "orderCode": "0030987", "load": 636259, "distance": 14, "items": [{"code": "187092", "itemType": "Adult", "weight": 7800, "quantity": 30, "cbm": 0.01434, "description": ""}, {"code": "187093", "itemType": "Ensure", "weight": 14016, "quantity": 48, "cbm": 0.023712, "description": ""}, {"code": "187094", "itemType": "Ensure", "weight": 2068, "quantity": 4, "cbm": 0.00518, "description": ""}, {"code": "187095", "itemType": "Ensure", "weight": 13824, "quantity": 48, "cbm": 0.024528, "description": ""}]}, {"code": "3902637", "address": "Qu\u1eadn B\u00ecnh Th\u1ea1nh", "lat": 10.804089, "lng": 106.6924787, "arrivalTime": "2019-12-05 10:54:17", "departureTime": "2019-12-05 11:01:08", "description": "", "orderCode": "0031140", "load": 776419, "distance": 15, "items": [{"code": "187146", "itemType": "Ensure", "weight": 140160, "quantity": 480, "cbm": 0.23712, "description": ""}]}, {"code": "3874037", "address": "Qu\u1eadn B\u00ecnh Th\u1ea1nh", "lat": 10.8056378, "lng": 106.6959579, "arrivalTime": "2019-12-05 11:03:41", "departureTime": "2019-12-05 11:18:41", "description": "", "orderCode": "0030885", "load": 787939, "distance": 15, "items": [{"code": "187068", "itemType": "Adult", "weight": 11520, "quantity": 24, "cbm": 0.03108, "description": ""}]}, {"code": "3873787", "address": "Qu\u1eadn B\u00ecnh Th\u1ea1nh", "lat": 10.8037837, "lng": 106.6941456, "arrivalTime": "2019-12-05 11:19:47", "departureTime": "2019-12-05 11:34:47", "description": "", "orderCode": "0031028", "load": 822499, "distance": 15, "items": [{"code": "187134", "itemType": "Ensure", "weight": 34560, "quantity": 120, "cbm": 0.06132, "description": ""}]}, {"code": "3873637", "address": "Qu\u1eadn B\u00ecnh Th\u1ea1nh", "lat": 10.8055491, "lng": 106.6950033, "arrivalTime": "2019-12-05 11:35:35", "departureTime": "2019-12-05 11:50:35", "description": "", "orderCode": "0031027", "load": 962659, "distance": 15, "items": [{"code": "187133", "itemType": "Ensure", "weight": 140160, "quantity": 480, "cbm": 0.23712, "description": ""}]}, {"code": "1178339", "address": "Qu\u1eadn 3", "lat": 10.7795808, "lng": 106.6798781, "arrivalTime": "2019-12-05 12:03:13", "departureTime": "2019-12-05 12:18:13", "description": "", "orderCode": "0030894", "load": 988057, "distance": 19, "items": [{"code": "187164", "itemType": "Grow", "weight": 13596, "quantity": 12, "cbm": 0.036384, "description": ""}, {"code": "187165", "itemType": "Pediasure", "weight": 11802, "quantity": 6, "cbm": 0.03072, "description": ""}]}, {"code": "1178339", "address": "Qu\u1eadn 3", "lat": 10.7795808, "lng": 106.6798781, "arrivalTime": "2019-12-05 12:03:13", "departureTime": "2019-12-05 12:18:13", "description": "", "orderCode": "0030893", "load": 1074851, "distance": 19, "items": [{"code": "187158", "itemType": "Pediasure", "weight": 2524, "quantity": 1, "cbm": 0.003603, "description": ""}, {"code": "187159", "itemType": "Pediasure", "weight": 27764, "quantity": 11, "cbm": 0.039633, "description": ""}, {"code": "187160", "itemType": "Grow", "weight": 4432, "quantity": 4, "cbm": 0.012128, "description": ""}, {"code": "187161", "itemType": "Grow", "weight": 12090, "quantity": 6, "cbm": 0.030738, "description": ""}, {"code": "187162", "itemType": "Grow", "weight": 21480, "quantity": 12, "cbm": 0.111708, "description": ""}, {"code": "187163", "itemType": "Pediasure", "weight": 18504, "quantity": 12, "cbm": 0.095244, "description": ""}]}, {"code": "1198139", "address": "Qu\u1eadn 8", "lat": 10.747863, "lng": 106.682092, "arrivalTime": "2019-12-05 12:32:00", "departureTime": "2019-12-05 12:47:00", "description": "", "orderCode": "0031052", "load": 1104635, "distance": 23, "items": [{"code": "187225", "itemType": "Grow", "weight": 29784, "quantity": 6, "cbm": 0.050796, "description": ""}]}, {"code": "4248837", "address": "Qu\u1eadn 8", "lat": 10.7509253, "lng": 106.6852613, "arrivalTime": "2019-12-05 12:48:43", "departureTime": "2019-12-05 12:57:09", "description": "", "orderCode": "0031057", "load": 1507811, "distance": 23, "items": [{"code": "186961", "itemType": "Adult", "weight": 253800, "quantity": 60, "cbm": 0.75084, "description": ""}, {"code": "186962", "itemType": "Grow", "weight": 30240, "quantity": 144, "cbm": 0.044208, "description": ""}, {"code": "186963", "itemType": "Grow", "weight": 119136, "quantity": 24, "cbm": 0.203184, "description": ""}]}, {"code": "R1_HCM", "address": "Qu\u1eadn T\u00e2n Ph\u00fa", "lat": 10.761124256132712, "lng": 106.63281628678588, "arrivalTime": "2019-12-05 13:20:45", "departureTime": "2019-12-05 13:50:45", "description": "", "orderCode": 0, "load": 0, "distance": 23}, {"code": "3660687", "address": "Qu\u1eadn 10", "lat": 10.7707367, "lng": 106.6594078, "arrivalTime": "2019-12-05 14:06:54", "departureTime": "2019-12-05 14:21:54", "description": "", "orderCode": "0031000", "load": 229200, "distance": 28, "items": [{"code": "187115", "itemType": "Ensure", "weight": 105120, "quantity": 360, "cbm": 0.17784, "description": ""}, {"code": "187116", "itemType": "Ensure", "weight": 124080, "quantity": 240, "cbm": 0.3108, "description": ""}]}, {"code": "3660687", "address": "Qu\u1eadn 10", "lat": 10.7707367, "lng": 106.6594078, "arrivalTime": "2019-12-05 14:06:54", "departureTime": "2019-12-05 14:21:54", "description": "", "orderCode": "0030999", "load": 653640, "distance": 28, "items": [{"code": "187112", "itemType": "Adult", "weight": 117000, "quantity": 450, "cbm": 0.2151, "description": ""}, {"code": "187113", "itemType": "Adult", "weight": 62160, "quantity": 120, "cbm": 0.1554, "description": ""}, {"code": "187114", "itemType": "Ensure", "weight": 245280, "quantity": 840, "cbm": 0.41496, "description": ""}]}, {"code": "4173837", "address": "Qu\u1eadn 5", "lat": 10.7531109, "lng": 106.6694218, "arrivalTime": "2019-12-05 14:32:11", "departureTime": "2019-12-05 14:44:14", "description": "", "orderCode": "0031115", "load": 1661640, "distance": 31, "items": [{"code": "187022", "itemType": "Grow", "weight": 141120, "quantity": 672, "cbm": 0.206304, "description": ""}, {"code": "187023", "itemType": "Grow", "weight": 866880, "quantity": 4128, "cbm": 1.267296, "description": ""}]}, {"code": "R1_HCM", "address": "Qu\u1eadn T\u00e2n Ph\u00fa", "lat": 10.761124256132712, "lng": 106.63281628678588, "arrivalTime": "2019-12-05 14:59:07", "departureTime": "2019-12-05 15:29:07", "description": "", "orderCode": 0, "load": 0, "distance": 31}, {"code": "1455339", "address": "Qu\u1eadn 6", "lat": 10.7570934, "lng": 106.6315734, "arrivalTime": "2019-12-05 15:35:07", "departureTime": "2019-12-05 15:50:07", "description": "", "orderCode": "0031117", "load": 37008, "distance": 33, "items": [{"code": "187043", "itemType": "Pediasure", "weight": 37008, "quantity": 24, "cbm": 0.190488, "description": ""}]}, {"code": "1455339", "address": "Qu\u1eadn 6", "lat": 10.7570934, "lng": 106.6315734, "arrivalTime": "2019-12-05 15:35:07", "departureTime": "2019-12-05 15:50:07", "description": "", "orderCode": "0031054", "load": 241728, "distance": 33, "items": [{"code": "187230", "itemType": "Similac", "weight": 3120, "quantity": 6, "cbm": 0.00777, "description": ""}, {"code": "187231", "itemType": "Grow", "weight": 201600, "quantity": 960, "cbm": 0.29472, "description": ""}]}, {"code": "1455339", "address": "Qu\u1eadn 6", "lat": 10.7570934, "lng": 106.6315734, "arrivalTime": "2019-12-05 15:35:07", "departureTime": "2019-12-05 15:50:07", "description": "", "orderCode": "0031053", "load": 354648, "distance": 33, "items": [{"code": "187226", "itemType": "Grow", "weight": 13404, "quantity": 12, "cbm": 0.036384, "description": ""}, {"code": "187227", "itemType": "Grow", "weight": 13596, "quantity": 12, "cbm": 0.036384, "description": ""}, {"code": "187228", "itemType": "Grow", "weight": 42960, "quantity": 24, "cbm": 0.223416, "description": ""}, {"code": "187229", "itemType": "Grow", "weight": 42960, "quantity": 24, "cbm": 0.223416, "description": ""}]}, {"code": "R1_HCM", "address": "Qu\u1eadn T\u00e2n Ph\u00fa", "lat": 10.761124256132712, "lng": 106.63281628678588, "arrivalTime": "2019-12-05 15:56:07", "departureTime": "2019-12-05 15:56:07", "description": "", "orderCode": 0, "load": 0, "distance": 33}], "distance": 33}, {"vehicle": {"group": "1.7XT", "code": "R1-XT1.7T-02", "lat": 10.761124256132712, "lng": 106.63281628678588, "endLat": 10.761124256132712, "endLng": 106.63281628678588, "startWorkingTime": "2019-12-05 09:00:00.0", "endWorkingTime": "2019-12-05 16:00:00.0", "availableCapacity": 1700000, "availableCbm": 1360.8}, "elements": [{"code": "R1_HCM", "address": "Qu\u1eadn T\u00e2n Ph\u00fa", "lat": 10.761124256132712, "lng": 106.63281628678588, "arrivalTime": "2019-12-05 09:00:00", "departureTime": "2019-12-05 09:00:00", "description": "", "orderCode": 0, "load": 0, "distance": 0}, {"code": "2372239", "address": "Qu\u1eadn B\u00ecnh T\u00e2n", "lat": 10.7572535, "lng": 106.6190378, "arrivalTime": "2019-12-05 09:06:56", "departureTime": "2019-12-05 09:21:56", "description": "", "orderCode": "0031056", "load": 20880, "distance": 2, "items": [{"code": "186959", "itemType": "Similac", "weight": 17400, "quantity": 10, "cbm": 0.02457, "description": ""}, {"code": "186960", "itemType": "Similac", "weight": 3480, "quantity": 2, "cbm": 0.004914, "description": ""}]}, {"code": "2372239", "address": "Qu\u1eadn B\u00ecnh T\u00e2n", "lat": 10.7572535, "lng": 106.6190378, "arrivalTime": "2019-12-05 09:06:56", "departureTime": "2019-12-05 09:21:56", "description": "", "orderCode": "0030895", "load": 67746, "distance": 2, "items": [{"code": "187166", "itemType": "Grow", "weight": 13296, "quantity": 12, "cbm": 0.036384, "description": ""}, {"code": "187167", "itemType": "Grow", "weight": 12090, "quantity": 6, "cbm": 0.030738, "description": ""}, {"code": "187168", "itemType": "Grow", "weight": 21480, "quantity": 12, "cbm": 0.111708, "description": ""}]}, {"code": "1165189", "address": "Qu\u1eadn B\u00ecnh T\u00e2n", "lat": 10.758277, "lng": 106.6071335, "arrivalTime": "2019-12-05 09:25:53", "departureTime": "2019-12-05 09:40:53", "description": "", "orderCode": "0031116", "load": 597426, "distance": 3, "items": [{"code": "187024", "itemType": "Similac", "weight": 2928, "quantity": 6, "cbm": 0.007938, "description": ""}, {"code": "187025", "itemType": "Similac", "weight": 6300, "quantity": 6, "cbm": 0.017796, "description": ""}, {"code": "187026", "itemType": "Similac", "weight": 13200, "quantity": 12, "cbm": 0.036384, "description": ""}, {"code": "187027", "itemType": "Similac", "weight": 24996, "quantity": 12, "cbm": 0.069984, "description": ""}, {"code": "187028", "itemType": "Similac", "weight": 13200, "quantity": 12, "cbm": 0.036384, "description": ""}, {"code": "187029", "itemType": "Similac", "weight": 24996, "quantity": 12, "cbm": 0.069984, "description": ""}, {"code": "187030", "itemType": "Similac", "weight": 45120, "quantity": 24, "cbm": 0.231552, "description": ""}, {"code": "187031", "itemType": "Pediasure", "weight": 30288, "quantity": 12, "cbm": 0.043236, "description": ""}, {"code": "187032", "itemType": "Grow", "weight": 13596, "quantity": 12, "cbm": 0.036384, "description": ""}, {"code": "187033", "itemType": "Grow", "weight": 26400, "quantity": 24, "cbm": 0.03108, "description": ""}, {"code": "187034", "itemType": "Grow", "weight": 13296, "quantity": 12, "cbm": 0.036384, "description": ""}, {"code": "187035", "itemType": "Grow", "weight": 36270, "quantity": 18, "cbm": 0.092214, "description": ""}, {"code": "187036", "itemType": "Similac", "weight": 13404, "quantity": 12, "cbm": 0.036384, "description": ""}, {"code": "187037", "itemType": "Grow", "weight": 26808, "quantity": 24, "cbm": 0.072768, "description": ""}, {"code": "187038", "itemType": "Pediasure", "weight": 25608, "quantity": 24, "cbm": 0.071184, "description": ""}, {"code": "187039", "itemType": "Pediasure", "weight": 35406, "quantity": 18, "cbm": 0.09216, "description": ""}, {"code": "187040", "itemType": "Pediasure", "weight": 18504, "quantity": 12, "cbm": 0.095244, "description": ""}, {"code": "187041", "itemType": "Grow", "weight": 148920, "quantity": 30, "cbm": 0.25398, "description": ""}, {"code": "187042", "itemType": "Similac", "weight": 10440, "quantity": 6, "cbm": 0.014742, "description": ""}]}, {"code": "1165189", "address": "Qu\u1eadn B\u00ecnh T\u00e2n", "lat": 10.758277, "lng": 106.6071335, "arrivalTime": "2019-12-05 09:25:53", "departureTime": "2019-12-05 09:40:53", "description": "", "orderCode": "0031048", "load": 615642, "distance": 3, "items": [{"code": "187219", "itemType": "Similac", "weight": 18216, "quantity": 18, "cbm": 0.0261, "description": ""}]}, {"code": "1165189", "address": "Qu\u1eadn B\u00ecnh T\u00e2n", "lat": 10.758277, "lng": 106.6071335, "arrivalTime": "2019-12-05 09:25:53", "departureTime": "2019-12-05 09:40:53", "description": "", "orderCode": "0031137", "load": 630342, "distance": 3, "items": [{"code": "187058", "itemType": "Adult", "weight": 14700, "quantity": 6, "cbm": 0.07854, "description": ""}]}, {"code": "1165189", "address": "Qu\u1eadn B\u00ecnh T\u00e2n", "lat": 10.758277, "lng": 106.6071335, "arrivalTime": "2019-12-05 09:25:53", "departureTime": "2019-12-05 09:40:53", "description": "", "orderCode": "0031049", "load": 643746, "distance": 3, "items": [{"code": "187220", "itemType": "Similac", "weight": 13404, "quantity": 12, "cbm": 0.036384, "description": ""}]}, {"code": "3827837", "address": "Qu\u1eadn B\u00ecnh T\u00e2n", "lat": 10.756274389238, "lng": 106.586631428242, "arrivalTime": "2019-12-05 09:48:29", "departureTime": "2019-12-05 10:03:29", "description": "", "orderCode": "0031119", "load": 667926, "distance": 5, "items": [{"code": "187048", "itemType": "Grow", "weight": 24180, "quantity": 12, "cbm": 0.061476, "description": ""}]}, {"code": "2056989", "address": "Qu\u1eadn B\u00ecnh T\u00e2n", "lat": 10.7333463724263, "lng": 106.608808730194, "arrivalTime": "2019-12-05 10:14:18", "departureTime": "2019-12-05 10:29:18", "description": "", "orderCode": "0031138", "load": 670060, "distance": 8, "items": [{"code": "187059", "itemType": "Ensure", "weight": 2134, "quantity": 2, "cbm": 0.005932, "description": ""}]}, {"code": "4121937", "address": "Qu\u1eadn B\u00ecnh T\u00e2n", "lat": 10.7400401, "lng": 106.6149232, "arrivalTime": "2019-12-05 10:41:12", "departureTime": "2019-12-05 10:47:14", "description": "", "orderCode": "0030992", "load": 675270, "distance": 11, "items": [{"code": "187100", "itemType": "Ensure", "weight": 5210, "quantity": 10, "cbm": 0.01295, "description": ""}]}, {"code": "2839837", "address": "Qu\u1eadn 6", "lat": 10.7405312, "lng": 106.6219827, "arrivalTime": "2019-12-05 10:51:42", "departureTime": "2019-12-05 11:06:42", "description": "", "orderCode": "0031047", "load": 844470, "distance": 12, "items": [{"code": "187218", "itemType": "Adult", "weight": 169200, "quantity": 40, "cbm": 0.50056, "description": ""}]}, {"code": "1191189", "address": "Qu\u1eadn 6", "lat": 10.747814, "lng": 106.634814, "arrivalTime": "2019-12-05 11:12:31", "departureTime": "2019-12-05 11:27:31", "description": "", "orderCode": "0031051", "load": 867030, "distance": 13, "items": [{"code": "187224", "itemType": "Similac", "weight": 22560, "quantity": 12, "cbm": 0.115776, "description": ""}]}, {"code": "1160239", "address": "Qu\u1eadn 6", "lat": 10.750806, "lng": 106.649359, "arrivalTime": "2019-12-05 11:32:49", "departureTime": "2019-12-05 11:47:49", "description": "", "orderCode": "0031046", "load": 1036230, "distance": 14, "items": [{"code": "187217", "itemType": "Adult", "weight": 169200, "quantity": 40, "cbm": 0.50056, "description": ""}]}, {"code": "R1_HCM", "address": "Qu\u1eadn T\u00e2n Ph\u00fa", "lat": 10.761124256132712, "lng": 106.63281628678588, "arrivalTime": "2019-12-05 11:55:36", "departureTime": "2019-12-05 12:25:36", "description": "", "orderCode": 0, "load": 0, "distance": 14}, {"code": "1169489", "address": "Qu\u1eadn 6", "lat": 10.750212, "lng": 106.63042, "arrivalTime": "2019-12-05 12:32:48", "departureTime": "2019-12-05 12:47:48", "description": "", "orderCode": "0030892", "load": 562320, "distance": 16, "items": [{"code": "187155", "itemType": "Adult", "weight": 169200, "quantity": 40, "cbm": 0.50056, "description": ""}, {"code": "187156", "itemType": "Grow", "weight": 28140, "quantity": 134, "cbm": 0.041138, "description": ""}, {"code": "187157", "itemType": "Grow", "weight": 364980, "quantity": 1738, "cbm": 0.533566, "description": ""}]}, {"code": "1191189", "address": "Qu\u1eadn 6", "lat": 10.747814, "lng": 106.634814, "arrivalTime": "2019-12-05 12:50:22", "departureTime": "2019-12-05 13:05:22", "description": "", "orderCode": "0031050", "load": 601218, "distance": 16, "items": [{"code": "187221", "itemType": "Similac", "weight": 13200, "quantity": 12, "cbm": 0.036384, "description": ""}, {"code": "187222", "itemType": "Similac", "weight": 12498, "quantity": 6, "cbm": 0.034992, "description": ""}, {"code": "187223", "itemType": "Similac", "weight": 13200, "quantity": 12, "cbm": 0.036384, "description": ""}]}, {"code": "1454389", "address": "Qu\u1eadn 6", "lat": 10.745072, "lng": 106.637287, "arrivalTime": "2019-12-05 13:07:40", "departureTime": "2019-12-05 13:22:40", "description": "", "orderCode": "0030891", "load": 1024218, "distance": 16, "items": [{"code": "187153", "itemType": "Adult", "weight": 25380, "quantity": 6, "cbm": 0.075084, "description": ""}, {"code": "187154", "itemType": "Adult", "weight": 397620, "quantity": 94, "cbm": 1.176316, "description": ""}]}, {"code": "R1_HCM", "address": "Qu\u1eadn T\u00e2n Ph\u00fa", "lat": 10.761124256132712, "lng": 106.63281628678588, "arrivalTime": "2019-12-05 13:29:43", "departureTime": "2019-12-05 13:29:43", "description": "", "orderCode": 0, "load": 0, "distance": 16}], "distance": 16}, {"vehicle": {"group": "0.6BT", "code": "R1-BT0.5T-01", "lat": 10.761124256132712, "lng": 106.63281628678588, "endLat": 10.761124256132712, "endLng": 106.63281628678588, "startWorkingTime": "2019-12-05 09:00:00.0", "endWorkingTime": null, "availableCapacity": 500000, "availableCbm": 115.2}, "elements": [{"code": "R1_HCM", "address": "Qu\u1eadn T\u00e2n Ph\u00fa", "lat": 10.761124256132712, "lng": 106.63281628678588, "arrivalTime": "2019-12-05 09:00:00", "departureTime": "2019-12-05 09:00:00", "description": "", "orderCode": 0, "load": 0, "distance": 0}, {"code": "3280237", "address": "Qu\u1eadn T\u00e2n B\u00ecnh", "lat": 10.7793199857336, "lng": 106.651723117374, "arrivalTime": "2019-12-05 09:13:17", "departureTime": "2019-12-05 09:28:17", "description": "", "orderCode": "0030896", "load": 33840, "distance": 4, "items": [{"code": "187169", "itemType": "Adult", "weight": 33840, "quantity": 8, "cbm": 0.100112, "description": ""}]}, {"code": "3280237", "address": "Qu\u1eadn T\u00e2n B\u00ecnh", "lat": 10.7793199857336, "lng": 106.651723117374, "arrivalTime": "2019-12-05 09:13:17", "departureTime": "2019-12-05 09:28:17", "description": "", "orderCode": "0031118", "load": 47214, "distance": 4, "items": [{"code": "187044", "itemType": "Grow", "weight": 3324, "quantity": 3, "cbm": 0.009096, "description": ""}, {"code": "187045", "itemType": "Grow", "weight": 3399, "quantity": 3, "cbm": 0.009096, "description": ""}, {"code": "187046", "itemType": "Grow", "weight": 3300, "quantity": 3, "cbm": 0.003885, "description": ""}, {"code": "187047", "itemType": "Grow", "weight": 3351, "quantity": 3, "cbm": 0.009096, "description": ""}]}, {"code": "4100637", "address": "Qu\u1eadn T\u00e2n B\u00ecnh", "lat": 10.8001257, "lng": 106.6647141, "arrivalTime": "2019-12-05 09:40:10", "departureTime": "2019-12-05 09:46:22", "description": "", "orderCode": "0030889", "load": 78306, "distance": 7, "items": [{"code": "187076", "itemType": "Similac", "weight": 12480, "quantity": 24, "cbm": 0.03108, "description": ""}, {"code": "187077", "itemType": "Similac", "weight": 6204, "quantity": 12, "cbm": 0.01554, "description": ""}, {"code": "187078", "itemType": "Similac", "weight": 12408, "quantity": 24, "cbm": 0.03108, "description": ""}]}, {"code": "1151239", "address": "Qu\u1eadn Ph\u00fa Nhu\u1eadn", "lat": 10.795844, "lng": 106.668451, "arrivalTime": "2019-12-05 09:49:18", "departureTime": "2019-12-05 10:04:18", "description": "", "orderCode": "0031045", "load": 113346, "distance": 7, "items": [{"code": "187216", "itemType": "Ensure", "weight": 35040, "quantity": 120, "cbm": 0.05928, "description": ""}]}, {"code": "1151239", "address": "Qu\u1eadn Ph\u00fa Nhu\u1eadn", "lat": 10.795844, "lng": 106.668451, "arrivalTime": "2019-12-05 09:49:18", "departureTime": "2019-12-05 10:04:18", "description": "", "orderCode": "0031044", "load": 217426, "distance": 7, "items": [{"code": "187210", "itemType": "Similac", "weight": 1840, "quantity": 4, "cbm": 0.005072, "description": ""}, {"code": "187211", "itemType": "Similac", "weight": 3030, "quantity": 6, "cbm": 0.007698, "description": ""}, {"code": "187212", "itemType": "Grow", "weight": 13596, "quantity": 12, "cbm": 0.036384, "description": ""}, {"code": "187213", "itemType": "Grow", "weight": 13200, "quantity": 12, "cbm": 0.01554, "description": ""}, {"code": "187214", "itemType": "Pediasure", "weight": 35406, "quantity": 18, "cbm": 0.09216, "description": ""}, {"code": "187215", "itemType": "Pediasure", "weight": 37008, "quantity": 24, "cbm": 0.190488, "description": ""}]}, {"code": "4100637", "address": "Qu\u1eadn T\u00e2n B\u00ecnh", "lat": 10.8001257, "lng": 106.6647141, "arrivalTime": "2019-12-05 10:08:53", "departureTime": "2019-12-05 10:15:02", "description": "", "orderCode": "0030991", "load": 242242, "distance": 8, "items": [{"code": "187099", "itemType": "Similac", "weight": 24816, "quantity": 48, "cbm": 0.06216, "description": ""}]}, {"code": "1140789", "address": "Qu\u1eadn T\u00e2n B\u00ecnh", "lat": 10.80007, "lng": 106.667284, "arrivalTime": "2019-12-05 10:15:52", "departureTime": "2019-12-05 10:30:52", "description": "", "orderCode": "0030995", "load": 257824, "distance": 8, "items": [{"code": "187106", "itemType": "Similac", "weight": 3102, "quantity": 6, "cbm": 0.007698, "description": ""}, {"code": "187107", "itemType": "Similac", "weight": 12480, "quantity": 24, "cbm": 0.03108, "description": ""}]}, {"code": "2272789", "address": "Qu\u1eadn T\u00e2n B\u00ecnh", "lat": 10.800158, "lng": 106.6676491, "arrivalTime": "2019-12-05 10:30:58", "departureTime": "2019-12-05 10:45:58", "description": "", "orderCode": "0030877", "load": 264052, "distance": 8, "items": [{"code": "187013", "itemType": "Similac", "weight": 3126, "quantity": 6, "cbm": 0.007698, "description": ""}, {"code": "187014", "itemType": "Similac", "weight": 3102, "quantity": 6, "cbm": 0.007698, "description": ""}]}, {"code": "3842737", "address": "Qu\u1eadn T\u00e2n B\u00ecnh", "lat": 10.7909485486214, "lng": 106.653799662635, "arrivalTime": "2019-12-05 10:56:18", "departureTime": "2019-12-05 11:11:18", "description": "", "orderCode": "0030984", "load": 270268, "distance": 11, "items": [{"code": "187086", "itemType": "Adult", "weight": 6216, "quantity": 12, "cbm": 0.01554, "description": ""}]}, {"code": "3842737", "address": "Qu\u1eadn T\u00e2n B\u00ecnh", "lat": 10.7909485486214, "lng": 106.653799662635, "arrivalTime": "2019-12-05 10:56:18", "departureTime": "2019-12-05 11:11:18", "description": "", "orderCode": "0030985", "load": 327112, "distance": 11, "items": [{"code": "187087", "itemType": "Adult", "weight": 15600, "quantity": 60, "cbm": 0.02868, "description": ""}, {"code": "187088", "itemType": "Ensure", "weight": 35040, "quantity": 120, "cbm": 0.05928, "description": ""}, {"code": "187089", "itemType": "Ensure", "weight": 6204, "quantity": 12, "cbm": 0.01554, "description": ""}]}, {"code": "R1_HCM", "address": "Qu\u1eadn T\u00e2n Ph\u00fa", "lat": 10.761124256132712, "lng": 106.63281628678588, "arrivalTime": "2019-12-05 11:26:59", "departureTime": "2019-12-05 11:56:59", "description": "", "orderCode": 0, "load": 0, "distance": 11}, {"code": "3873137", "address": "Huy\u1ec7n C\u1ee7 Chi", "lat": 10.9279724869383, "lng": 106.558398725375, "arrivalTime": "2019-12-05 13:17:28", "departureTime": "2019-12-05 13:32:28", "description": "", "orderCode": "0031001", "load": 275052, "distance": 37, "items": [{"code": "187117", "itemType": "Ensure", "weight": 119136, "quantity": 408, "cbm": 0.201552, "description": ""}, {"code": "187118", "itemType": "Ensure", "weight": 12408, "quantity": 24, "cbm": 0.03108, "description": ""}, {"code": "187119", "itemType": "Ensure", "weight": 12504, "quantity": 24, "cbm": 0.03108, "description": ""}, {"code": "187120", "itemType": "Ensure", "weight": 12504, "quantity": 24, "cbm": 0.03108, "description": ""}, {"code": "187121", "itemType": "Ensure", "weight": 14820, "quantity": 60, "cbm": 0.02868, "description": ""}, {"code": "187122", "itemType": "Ensure", "weight": 103680, "quantity": 360, "cbm": 0.18396, "description": ""}]}, {"code": "3873137", "address": "Huy\u1ec7n C\u1ee7 Chi", "lat": 10.9279724869383, "lng": 106.558398725375, "arrivalTime": "2019-12-05 13:17:28", "departureTime": "2019-12-05 13:32:28", "description": "", "orderCode": "0030881", "load": 378312, "distance": 37, "items": [{"code": "187062", "itemType": "Ensure", "weight": 16380, "quantity": 60, "cbm": 0.02868, "description": ""}, {"code": "187063", "itemType": "Adult", "weight": 12432, "quantity": 24, "cbm": 0.03108, "description": ""}, {"code": "187064", "itemType": "Ensure", "weight": 74448, "quantity": 144, "cbm": 0.18648, "description": ""}]}, {"code": "R1_HCM", "address": "Qu\u1eadn T\u00e2n Ph\u00fa", "lat": 10.761124256132712, "lng": 106.63281628678588, "arrivalTime": "2019-12-05 14:48:10", "departureTime": "2019-12-05 14:48:10", "description": "", "orderCode": 0, "load": 0, "distance": 37}], "distance": 37}, {"vehicle": {"group": "0.6BT", "code": "R1-BT0.5T-02", "lat": 10.761124256132712, "lng": 106.63281628678588, "endLat": 10.761124256132712, "endLng": 106.63281628678588, "startWorkingTime": "2019-12-05 09:00:00.0", "endWorkingTime": null, "availableCapacity": 500000, "availableCbm": 115.2}, "elements": [{"code": "R1_HCM", "address": "Qu\u1eadn T\u00e2n Ph\u00fa", "lat": 10.761124256132712, "lng": 106.63281628678588, "arrivalTime": "2019-12-05 09:00:00", "departureTime": "2019-12-05 09:00:00", "description": "", "orderCode": 0, "load": 0, "distance": 0}, {"code": "3532187", "address": "Qu\u1eadn B\u00ecnh T\u00e2n", "lat": 10.799911629357, "lng": 106.586882124715, "arrivalTime": "2019-12-05 09:28:28", "departureTime": "2019-12-05 09:43:28", "description": "", "orderCode": "0030898", "load": 37008, "distance": 9, "items": [{"code": "187172", "itemType": "Pediasure", "weight": 37008, "quantity": 24, "cbm": 0.190488, "description": ""}]}, {"code": "3532187", "address": "Qu\u1eadn B\u00ecnh T\u00e2n", "lat": 10.799911629357, "lng": 106.586882124715, "arrivalTime": "2019-12-05 09:28:28", "departureTime": "2019-12-05 09:43:28", "description": "", "orderCode": "0030897", "load": 123210, "distance": 9, "items": [{"code": "187170", "itemType": "Grow", "weight": 27192, "quantity": 24, "cbm": 0.072768, "description": ""}, {"code": "187171", "itemType": "Pediasure", "weight": 59010, "quantity": 30, "cbm": 0.1536, "description": ""}]}, {"code": "3532187", "address": "Qu\u1eadn B\u00ecnh T\u00e2n", "lat": 10.799911629357, "lng": 106.586882124715, "arrivalTime": "2019-12-05 09:46:55", "departureTime": "2019-12-05 10:01:55", "description": "", "orderCode": "0030899", "load": 137910, "distance": 9, "items": [{"code": "187173", "itemType": "Ensure", "weight": 14700, "quantity": 6, "cbm": 0.081396, "description": ""}]}, {"code": "3873337", "address": "Qu\u1eadn T\u00e2n Ph\u00fa", "lat": 10.7797173, "lng": 106.6220312, "arrivalTime": "2019-12-05 10:51:52", "departureTime": "2019-12-05 11:06:52", "description": "", "orderCode": "0031055", "load": 191080, "distance": 15, "items": [{"code": "186951", "itemType": "Similac", "weight": 4166, "quantity": 2, "cbm": 0.011664, "description": ""}, {"code": "186952", "itemType": "Similac", "weight": 4166, "quantity": 2, "cbm": 0.011664, "description": ""}, {"code": "186953", "itemType": "Pediasure", "weight": 10096, "quantity": 4, "cbm": 0.014412, "description": ""}, {"code": "186954", "itemType": "Grow", "weight": 10075, "quantity": 5, "cbm": 0.025615, "description": ""}, {"code": "186955", "itemType": "Grow", "weight": 2015, "quantity": 1, "cbm": 0.005123, "description": ""}, {"code": "186956", "itemType": "Similac", "weight": 2234, "quantity": 2, "cbm": 0.006064, "description": ""}, {"code": "186957", "itemType": "Ensure", "weight": 14016, "quantity": 48, "cbm": 0.023712, "description": ""}, {"code": "186958", "itemType": "Ensure", "weight": 6402, "quantity": 6, "cbm": 0.017796, "description": ""}]}, {"code": "2450039", "address": "Qu\u1eadn T\u00e2n Ph\u00fa", "lat": 10.7813165, "lng": 106.6414725, "arrivalTime": "2019-12-05 11:45:00", "departureTime": "2019-12-05 12:00:00", "description": "", "orderCode": "0031041", "load": 234040, "distance": 17, "items": [{"code": "187207", "itemType": "Grow", "weight": 42960, "quantity": 24, "cbm": 0.223416, "description": ""}]}, {"code": "2450039", "address": "Qu\u1eadn T\u00e2n Ph\u00fa", "lat": 10.7813165, "lng": 106.6414725, "arrivalTime": "2019-12-05 11:45:00", "departureTime": "2019-12-05 12:00:00", "description": "", "orderCode": "0031042", "load": 277000, "distance": 17, "items": [{"code": "187208", "itemType": "Grow", "weight": 42960, "quantity": 24, "cbm": 0.223416, "description": ""}]}, {"code": "2450039", "address": "Qu\u1eadn T\u00e2n Ph\u00fa", "lat": 10.7813165, "lng": 106.6414725, "arrivalTime": "2019-12-05 11:45:00", "departureTime": "2019-12-05 12:00:00", "description": "", "orderCode": "0031043", "load": 319960, "distance": 17, "items": [{"code": "187209", "itemType": "Grow", "weight": 42960, "quantity": 24, "cbm": 0.223416, "description": ""}]}, {"code": "R1_HCM", "address": "Qu\u1eadn T\u00e2n Ph\u00fa", "lat": 10.761124256132712, "lng": 106.63281628678588, "arrivalTime": "2019-12-05 12:09:00", "departureTime": "2019-12-05 12:39:00", "description": "", "orderCode": 0, "load": 0, "distance": 17}, {"code": "2351939", "address": "Qu\u1eadn T\u00e2n Ph\u00fa", "lat": 10.81403, "lng": 106.620836, "arrivalTime": "2019-12-05 13:02:01", "departureTime": "2019-12-05 13:17:01", "description": "", "orderCode": "0031040", "load": 31959, "distance": 24, "items": [{"code": "187201", "itemType": "Similac", "weight": 2083, "quantity": 1, "cbm": 0.005832, "description": ""}, {"code": "187202", "itemType": "Adult", "weight": 1036, "quantity": 2, "cbm": 0.00259, "description": ""}, {"code": "187203", "itemType": "Grow", "weight": 4066, "quantity": 2, "cbm": 0.010244, "description": ""}, {"code": "187204", "itemType": "Grow", "weight": 3580, "quantity": 2, "cbm": 0.018618, "description": ""}, {"code": "187205", "itemType": "Ensure", "weight": 1034, "quantity": 2, "cbm": 0.00259, "description": ""}, {"code": "187206", "itemType": "Grow", "weight": 20160, "quantity": 96, "cbm": 0.029472, "description": ""}]}, {"code": "3873387", "address": "Huy\u1ec7n H\u00f3c M\u00f4n", "lat": 10.8824632, "lng": 106.5941623, "arrivalTime": "2019-12-05 13:46:25", "departureTime": "2019-12-05 14:01:25", "description": "", "orderCode": "0031026", "load": 44463, "distance": 33, "items": [{"code": "187132", "itemType": "Similac", "weight": 12504, "quantity": 24, "cbm": 0.030792, "description": ""}]}, {"code": "4036437", "address": "Huy\u1ec7n C\u1ee7 Chi", "lat": 10.9748539, "lng": 106.4751815, "arrivalTime": "2019-12-05 14:57:43", "departureTime": "2019-12-05 15:04:32", "description": "", "orderCode": "0030886", "load": 178383, "distance": 51, "items": [{"code": "187069", "itemType": "Adult", "weight": 39000, "quantity": 150, "cbm": 0.0717, "description": ""}, {"code": "187070", "itemType": "Adult", "weight": 12432, "quantity": 24, "cbm": 0.03108, "description": ""}, {"code": "187071", "itemType": "Ensure", "weight": 70080, "quantity": 240, "cbm": 0.11856, "description": ""}, {"code": "187072", "itemType": "Ensure", "weight": 12408, "quantity": 24, "cbm": 0.03108, "description": ""}]}, {"code": "3874937", "address": "Huy\u1ec7n C\u1ee7 Chi", "lat": 10.9748138, "lng": 106.4773142, "arrivalTime": "2019-12-05 15:05:27", "departureTime": "2019-12-05 15:13:02", "description": "", "orderCode": "0031029", "load": 439887, "distance": 51, "items": [{"code": "187135", "itemType": "Ensure", "weight": 65520, "quantity": 240, "cbm": 0.11472, "description": ""}, {"code": "187136", "itemType": "Adult", "weight": 39000, "quantity": 150, "cbm": 0.0717, "description": ""}, {"code": "187137", "itemType": "Adult", "weight": 24864, "quantity": 48, "cbm": 0.06216, "description": ""}, {"code": "187138", "itemType": "Ensure", "weight": 70080, "quantity": 240, "cbm": 0.11856, "description": ""}, {"code": "187139", "itemType": "Ensure", "weight": 62040, "quantity": 120, "cbm": 0.1554, "description": ""}]}, {"code": "R1_HCM", "address": "Qu\u1eadn T\u00e2n Ph\u00fa", "lat": 10.761124256132712, "lng": 106.63281628678588, "arrivalTime": "2019-12-05 16:47:43", "departureTime": "2019-12-05 16:47:43", "description": "", "orderCode": 0, "load": 0, "distance": 51}], "distance": 51}], "unScheduledRequests": [], "statistics": {"totalDistance": 189, "numVehicles": 5, "numTrips": 10, "longestTrip": 52, "shortestTrip": 2, "averageTripDistance": 18.9, "maximumTransferRatio": 97.74352941176471, "minimumTransferRatio": 20.86164705882353, "averageTransferRatio": 71.57637647058823, "distanceTripList": [[52], [23, 8, 2], [14, 2], [11, 26], [17, 34]], "loadTripList": [[94.2068], [88.69476470588236, 97.74352941176471, 20.86164705882353], [60.95470588235295, 60.24811764705882], [65.4224, 75.66239999999999], [63.992000000000004, 87.97739999999999]]}}]}